[
  {"year": 1985, "name": "Свидетель"},
  {"year": 1987, "name": "Спасение!"},
  {"year": 1987, "name": "Тюрьма"},
  {"year": 1988, "name": "Свежие лошади"},
  {"year": 1990, "name": "Западня"},
  {"year": 1990, "name": "Кожаное лицо: Техасская резня бензопилой 3"},
  {"year": 1990, "name": "Молодые стрелки 2"},
  {"year": 1990, "name": "Зеркальная кожа"},
  {"year": 1991, "name": "Бегущий индеец"},
  {"year": 1993, "name": "Точка кипения"},
  {"year": 1993, "name": "Рубин Каира"},
  {"year": 1993, "name": "Путь Карлито"},
  {"year": 1993, "name": "Молодые американцы"},
  {"year": 1994, "name": "Экипаж"},
  {"year": 1994, "name": "Путаница"},
  {"year": 1994, "name": "Евангелие от Гарри"},
  {"year": 1994, "name": "Американский якудза"},
  {"year": 1995, "name": "Пророчество"},
  {"year": 1995, "name": "Багровый прилив"},
  {"year": 1996, "name": "Портрет леди"},
  {"year": 1996, "name": "Дневной свет"},
  {"year": 1997, "name": "Солдат Джейн"},
  {"year": 1997, "name": "Исчезающая точка"},
  {"year": 1998, "name": "Идеальное убийство"},
  {"year": 1998, "name": "Психоз"},
  {"year": 1999, "name": "Прогулка по Луне"},
  {"year": 2000, "name": "28 дней"},
  {"year": 2001, "name": "Властелин колец: Братство Кольца"},
  {"year": 2002, "name": "Властелин колец: Две крепости"},
  {"year": 2003, "name": "Властелин колец: Возвращение короля"},
  {"year": 2004, "name": "Идальго"},
  {"year": 2005, "name": "Оправданная жестокость"},
  {"year": 2006, "name": "Капитан Алатристе"},
  {"year": 2007, "name": "Порок на экспорт"},
  {"year": 2008, "name": "Аппалуза"},
  {"year": 2008, "name": "Хороший"},
  {"year": 2009, "name": "Дорога"},
  {"year": 2011, "name": "Опасный метод"},
  {"year": 2012, "name": "На дороге"},
  {"year": 2012, "name": "У всех есть план"},
  {"year": 2014, "name": "Два лика января"},
  {"year": 2014, "name": "Вдалеке от людей"},
  {"year": 2014, "name": "Страна благоденствия"},
  {"year": 2016, "name": "Капитан Фантастик"},
  {"year": 2018, "name": "Зелёная книга"},
  {"year": 2020, "name": "Падение"},
  {"year": 2022, "name": "Преступления будущего"},
  {"year": 2022, "name": "Тринадцать жизней"}
]